README.md
setup.py
MarkFluentLog.egg-info/PKG-INFO
MarkFluentLog.egg-info/SOURCES.txt
MarkFluentLog.egg-info/dependency_links.txt
MarkFluentLog.egg-info/requires.txt
MarkFluentLog.egg-info/top_level.txt
mark_fluent_log/__init__.py
mark_fluent_log/object_2_log.py
test/__init__.py
test/one.py