Metadata-Version: 1.0
Name: MarkFluentLog
Version: 1.0.6
Summary: 工具类整理
Home-page: https://gitee.com/medincmedinc/mark_excel
Author: Mark
Author-email: 1782980833@qq.com
License: MIT Licence
Keywords: MarkFluentLog,mark
Platform: any
